turfpy/__init__.py
turfpy/__version__.py
turfpy/_compact.py
turfpy/boolean.py
turfpy/extra.py
turfpy/feature_conversion.py
turfpy/helper.py
turfpy/measurement.py
turfpy/meta.py
turfpy/misc.py
turfpy/random.py
turfpy/transformation.py
turfpy/dev_lib/__init__.py
turfpy/dev_lib/earcut.py
turfpy/dev_lib/spline.py
turfpy-0.0.8.dist-info/LICENSE
turfpy-0.0.8.dist-info/METADATA
turfpy-0.0.8.dist-info/WHEEL
turfpy-0.0.8.dist-info/top_level.txt
turfpy-0.0.8.dist-info/RECORD
