Metadata-Version: 2.1
Name: turfpy
Version: 0.0.8
Summary: A Python library for performing geospatial data analysis which reimplements turf.js.
Download-URL: https://github.com/omanges/turfpy/archive/0.0.8.zip
Author: Omkar Mestry, Sachin Kharude
Author-email: om.m.mestry@gmail.com, sachinkharude10@gmail.com
License: MIT
Project-URL: Documentation, https://turfpy.readthedocs.io
Project-URL: Source, https://github.com/omanges/turfpy
Keywords: Python Library for Turf
Classifier: Development Status :: 4 - Beta
Classifier: Intended Audience :: Developers
Classifier: Topic :: Software Development :: Libraries
Classifier: License :: OSI Approved :: MIT License
Classifier: Programming Language :: Python :: 3
Classifier: Programming Language :: Python :: 3 :: Only
Classifier: Programming Language :: Python :: 3.10
Classifier: Programming Language :: Python :: 3.11
Classifier: Programming Language :: Python :: 3.12
Classifier: Programming Language :: Python :: 3.13
License-File: LICENSE
Requires-Dist: geojson==3.1.0
Requires-Dist: geopandas==1.0.1
Requires-Dist: shapely==2.0.6
Requires-Dist: scipy==1.14.1
Requires-Dist: numpy==1.26.4
